admin_autoregister/__init__.py
admin_autoregister/admin.py
admin_autoregister/apps.py
admin_autoregister/mixins.py
admin_autoregister/migrations/__init__.py
django_admin_autoregister-1.1.0.dist-info/LICENSE
django_admin_autoregister-1.1.0.dist-info/METADATA
django_admin_autoregister-1.1.0.dist-info/WHEEL
django_admin_autoregister-1.1.0.dist-info/top_level.txt
django_admin_autoregister-1.1.0.dist-info/RECORD
