Metadata-Version: 2.1
Name: django-admin-autoregister
Version: 1.1.0
Summary: A Django app that registers all unregistered models to the admin automatically.
Home-page: https://github.com/janezkranjc/django-admin-autoregister
Author: Janez Kranjc
Author-email: janez.kranjc@gmail.com
License: MIT License
Classifier: Environment :: Web Environment
Classifier: Framework :: Django
Classifier: Framework :: Django :: 2.2
Classifier: Intended Audience :: Developers
Classifier: Operating System :: OS Independent
Classifier: Programming Language :: Python
Classifier: Programming Language :: Python :: 3.6
Classifier: Programming Language :: Python :: 3.7
Classifier: Topic :: Internet :: WWW/HTTP
Classifier: Topic :: Internet :: WWW/HTTP :: Dynamic Content
License-File: LICENSE
